sixs_json/__init__.py
sixs_json/wrap.py
sixs_json-0.1.4.1.dist-info/METADATA
sixs_json-0.1.4.1.dist-info/WHEEL
sixs_json-0.1.4.1.dist-info/top_level.txt
sixs_json-0.1.4.1.dist-info/RECORD
