Metadata-Version: 2.1
Name: sixs_json
Version: 0.1.4.1
Summary: The 6S atmospheric radiative transfer model modified with JSON output and a python wrapper
Author-email: Raphael Mabit <raphael.mabit@gmail.com>
License: GPL
